curlbomb
