Metadata-Version: 1.1
Name: curlbomb
Version: 1.4.1
Summary: A personal HTTP server for serving one-time-use shell scripts
Home-page: https://github.com/EnigmaCurry/curlbomb
Author: Ryan McGuire
Author-email: ryan@enigmacurry.com
License: MIT
Platform: UNKNOWN
Classifier: Development Status :: 4 - Beta
Classifier: Topic :: Utilities
Classifier: License :: OSI Approved :: MIT License
